awaish_pkg/__init__.py
awaish_pkg/stack.py
awaish_pkg/utility_functions.py
awaish_pkg-1.43.dist-info/LICENSE.txt
awaish_pkg-1.43.dist-info/METADATA
awaish_pkg-1.43.dist-info/WHEEL
awaish_pkg-1.43.dist-info/top_level.txt
awaish_pkg-1.43.dist-info/RECORD
