Metadata-Version: 2.1
Name: awaish_pkg
Version: 1.43
Summary: A simple package offering a collection of useful functions for enhanced productivity.
Home-page: https://github.com/abuawaish/awaish_pkg
Author: abuawaish
Author-email: abuawaish7@gmail.com
License: MIT
Keywords: funny
Classifier: Programming Language :: Python :: 3
Classifier: License :: OSI Approved :: MIT License
Classifier: Operating System :: OS Independent
Classifier: Intended Audience :: Education
Classifier: Development Status :: 5 - Production/Stable
License-File: LICENSE.txt
